Workbook
Name Hallo: Annahmen!$K$10:$K$10
Name Startjahr: Annahmen!$B$5:$B$5

Sheet Annahmen
A2: ANNAHMEN: | F2: Statisches Eingabefeld
A3: Finanz- und Liquiditätsplanung | F3: Variables Eingabefeld
F4: Verknüpfung mit grünes Feld
A5: Startjahr | B5: 2025 | G5: Ausgangsposition | I5: Veränderungen
I6: Folgejahr
A7: Variable: | B7: Investitionskredit | D7: Ratenkredit | G7: 60000
A8: die unten | B8: Betriebsmittelkredit | D8: Ratenkredit
A9: orange | B9: mtl. Gehaltserhöhung ab Folgejahr für Informatiker:innen | I9: 700
A10: hinterlegten | B10: Kapazitätsauslastung | G10: 0.9 | I10: 0.9
A11: Felder | B11: Netto-Stundensatz beim Kunden | G11: 80 | I11: 80
A12: nehmen | B12: Anzahl Krankheitstage pro Informatiker:in | G12: 11 | I12: 11
A13: hier auf Bezug | B13: Weitere Investitionen | D13: Server im Folgejahr | I13: 30000
A15: Kredit
B16: Investitionskredit | C16: =$G$7 -> 60000
B17: Zinsatz p.a. | C17: 0.05
B18: Laufzeit | C18: 6
B19: Rate monatlich | C19: =C16/C18/12 -> 833.33333
B20: Betriebsmittelkredit | C20: =$G$8 -> 0
B21: Zinsatz p.a. | C21: =C17 -> 0.05
B22: Laufzeit | C22: =C18 -> 6
B23: Rate monatlich | C23: =IF(C20=0,0,C20/C22/12) -> 0
B25: zur Vereinfachung werden hier nur Bankkredite und keine Anultitätsdahrlen verwendet
A27: Steuersatz für KöSt./GewSt.
K28: Veränderung | L28: verechenbare
A29: Wer erbringt die mit dem Kunden verechenbare Leistung? ==> gesucht sind die jährlich verechenbaren Stunden pro Vollzeit Informatiker:in | K29: Krankheitstage | L29: Stunden
A30: Ausgangspunkt | C30: 52 | D30: Wochen | E30: 5 | F30: Tage | G30: 8 | H30: Stunden | I30: =(C30*E30*G30) -> 2080 | L30: =I30 -> 2080
B31: Feiertage | E31: 11 | G31: 8 | I31: =-(E31*G31) -> -88 | L31: =I31 -> -88
B32: Urlaub | E32: 30 | G32: 8 | I32: =-(E32*G32) -> -240 | L32: =I32 -> -240
B33: Krankheit etc. | E33: =$G$12 -> 11 | G33: 8 | I33: =-(E33*G33) -> -88 | K33: =$I$12 -> 11 | L33: =I33 -> -88
A34: verfügbare Stunden / Informatiker | I34: =SUM(I30:I33) -> 1664 | L34: =I34 -> 1664
A35: nicht verreschenbare Stunden (E-Mails, Sitzungen, Telefonate, Recherche, Fehlerbehebung, etc.) | H35: 0.198718 | I35: =-(H35*I34) -> -330.66675 | L35: =-(H35*L34) -> -330.66675
A37: Verreschenbare Stunden | C37: 1 | D37: Kapazität | H37: Stunden p.a. | I37: =SUM(I34:I35) -> 1333.3332 | K37: Stunden p.a. | L37: =SUM(L34:L35) -> 1333.3332
E39: 2025 | F39: 2026 | H39: jan | I39: feb | J39: mar | K39: apr | L39: may | M39: jun | N39: jul | O39: aug | P39: sep | Q39: oct | R39: nov | S39: dec
A40: Umsatz
B41: Stundensatz | E41: =$G$11 -> 80 | F41: =$I$11 -> 80
B42: verrechnbare Stunden | E42: =I37 -> 1333.3332 | F42: =L37 -> 1333.3332
B43: Auslastung | E43: =$G$10 -> 0.9 | F43: =$I$10 -> 0.9
B44: geplante Auslastung | E44: =E42*E43 -> 1199.9999 | F44: =F42*F43 -> 1199.9999
B45: Anzahl Informatiker:in | E45: 15 | F45: 15
B46: Jahresumsatz | E46: =E41*E44*E45 -> 1439999.9 | F46: =F41*F44*F45 -> 1439999.9
E47: Stunden | F47: Beginn | G47: 2025 | H47: 2026 | I47: SV | J47: 2025 | K47: 2026
A48: Personalaufwand | I48: 0.219992
B49: Geschäftsführung | C49: 1 | D49: 7000 | E49: =$E$30*$G$30 -> 40 | F49: 45658 | G49: =D49*C49 -> 7000 | H49: =C49*D49 -> 7000 | I49: Monate | J49: =G49*$I$50*(1+$I$48) -> 102479.33 | K49: =H49*$I$50*(1+$I$48) -> 102479.33
B50: Buchhaltung | C50: 1 | D50: 3300 | E50: =$E$30*$G$30 -> 40 | F50: 45658 | G50: =D50*C50 -> 3300 | H50: =C50*D50 -> 3300 | I50: 12 | J50: =G50*$I$50*(1+$I$48) -> 48311.683 | K50: =H50*$I$50*(1+$I$48) -> 48311.683
B51: Assistenz | C51: 2 | D51: 3300 | E51: =$E$30*$G$30 -> 40 | F51: 45658 | G51: =D51*C51 -> 6600 | H51: =C51*D51 -> 6600 | J51: =G51*$I$50*(1+$I$48) -> 96623.366 | K51: =H51*$I$50*(1+$I$48) -> 96623.366
B52: Technik | C52: 1 | D52: 3300 | E52: =$E$30*$G$30 -> 40 | F52: 45658 | G52: =D52*C52 -> 3300 | H52: =C52*D52 -> 3300 | J52: =G52*$I$50*(1+$I$48) -> 48311.683 | K52: =H52*$I$50*(1+$I$48) -> 48311.683
B53: Informatiker | C53: 15 | D53: 4300 | E53: =$E$30*$G$30 -> 40 | F53: 45658 | G53: =D53*C53 -> 64500 | H53: =C53*D53 -> 64500 | J53: =G53*$I$50*(1+$I$48) -> 944273.81 | K53: =H53*$I$50*(1+$I$48) -> 944273.81
B54: Gehaltserhöhung | C54: 15 | D54: =$I$9 -> 700 | F54: 46023 | H54: =C54*D54 -> 10500 | J54: =G54*$I$50*(1+$I$48) -> 0 | K54: =H54*$I$50*(1+$I$48) -> 153718.99
B55: Summe Personalaufwand | J55: =SUM(J49:J54) -> 1239999.9 | K55: =SUM(K49:K54) -> 1393718.9
E57: 2025 | F57: 2026 | H57: jan | I57: feb | J57: mrz | K57: apr | L57: mai | M57: jun | N57: jul | O57: aug | P57: sep | Q57: okt | R57: nov | S57: dez
A58: Betrieblicher Aufwand
B59: Miete incl. Nebenkosten | C59: 250 | D59: 15 | E59: =C59*D59*12 -> 45000 | F59: =C59*D59*12 -> 45000
B60: so. Aufwand | E60: 100000 | F60: =E60 -> 100000 | H60: 0.073 | I60: 0.061 | J60: 0.07 | K60: 0.064 | L60: 0.237 | M60: 0.062 | N60: 0.072 | O60: 0.061 | P60: 0.105 | Q60: 0.064 | R60: 0.07 | S60: 0.061
H61: =H60*$E$60 -> 7300 | I61: =I60*$E$60 -> 6100 | J61: =J60*$E$60 -> 7000 | K61: =K60*$E$60 -> 6400 | L61: =L60*$E$60 -> 23700 | M61: =M60*$E$60 -> 6200 | N61: =N60*$E$60 -> 7200 | O61: =O60*$E$60 -> 6100 | ... S61: =S60*$E$60 -> 6100
E62: 2025 | F62: 2026
A63: Investitionen
A64: Auszahlungen | B64: PC/Drucker | D64: 45658 | E64: 39000 | F64: 0
A65: Nutzungsdauer | B65: 3
A66: Abschreibungen | E66: =E64/B65 -> 13000 | F66: =(E64+F64)/B65 -> 13000
A67: Auszahlung | B67: Büroausstattung | D67: 45658 | E67: 65000 | F67: 0
A68: Nutzungsdauer | B68: 13
A69: Anschreibungen | E69: =E67/B68 -> 5000 | F69: =(E67+F67)/B68 -> 5000
A70: Auszahlung | B70: Server | D70: 46023 | F70: =I13 -> 30000
A71: Nutzungsdauer | B71: 5
A72: Abschreibung | F72: =F70/B71 -> 6000
A73: Summe Auszahlungen | E73: =E64+E67 -> 104000 | F73: =F70 -> 30000
A74: Summe Abschreibungen | E74: =E66+E69 -> 18000 | F74: =F66+F69+F72 -> 24000
D77: 2024 | E77: 2025 | F77: 2026
A78: Bilanz
A79: Anlagenvermögen | D79: 0
A80: Umlaufvermögen | B80: Forderungen | D80: 0
B81: Kasse | D81: 100000
A82: Bilanzsumme | D82: =SUM(D80:D81) -> 100000
A83: Eigenkapital | B83: Stammkapital | D83: 50000
B84: Gewinnvortrag | D84: 30000
B85: Jahresabschluss | D85: 20000 | E85: k. Ausschüttung
A86: Fremdkapital | B86: Verbindlichkeiten L&L | D86: 0
A87: Bilanzsumme | D87: =SUM(D83:D85) -> 100000

Sheet GuV und Liquidität

Sheet Bilanz

Sheet Umsatz
N2: Gesamt | AA2: Gesamt
B3: Jan | C3: Feb | D3: Mrz | E3: Apr | F3: Mai | G3: Jun | H3: Jul | I3: Aug | J3: Sep | K3: Okt | L3: Nov | M3: Dez | N3: 2025 | O3: Jan | P3: Feb | Q3: Mrz | R3: Apr | S3: Mai | T3: Jun | U3: Jul | V3: Aug | W3: Sep | X3: Okt | Y3: Nov | Z3: Dez | AA3: 2026
A4: Umsatzverteilung | B4: 0.05 | C4: 0.1 | D4: 0.1 | E4: 0.08 | F4: 0.05 | G4: 0.1 | H4: 0.05 | I4: 0.05 | J4: 0.15 | K4: 0.1 | L4: 0.08 | M4: 0.09 | O4: 0.05 | P4: 0.1 | Q4: 0.1 | R4: 0.08 | S4: 0.05 | T4: 0.1 | U4: 0.05 | V4: 0.05 | W4: 0.15 | X4: 0.1 | Y4: 0.08 | Z4: 0.09
A6: Umsatzerlös Gesamt | B6: =$N$6*B4 -> 71999.995 | C6: =$N$6*C4 -> 143999.99 | D6: =$N$6*D4 -> 143999.99 | E6: =$N$6*E4 -> 115199.99 | F6: =$N$6*F4 -> 71999.995 | G6: =$N$6*G4 -> 143999.99 | H6: =$N$6*H4 -> 71999.995 | I6: =$N$6*I4 -> 71999.995 | ... M6: =$N$6*M4 -> 129599.99 | N6: =Annahmen!$E$46 -> 1439999.9 | O6: =$AA$6*O4 -> 71999.995 | P6: =$AA$6*P4 -> 143999.99 | Q6: =$AA$6*Q4 -> 143999.99 | R6: =$AA$6*R4 -> 115199.99 | S6: =$AA$6*S4 -> 71999.995 | T6: =$AA$6*T4 -> 143999.99 | U6: =$AA$6*U4 -> 71999.995 | V6: =$AA$6*V4 -> 71999.995 | ... Z6: =$AA$6*Z4 -> 129599.99 | AA6: =Annahmen!$F$46 -> 1439999.9
P8: GESAMT
A9: Nettobeträge | D9: Jan | E9: Feb | F9: Mar | G9: Apr | H9: May | I9: Jun | J9: Jul | K9: Aug | L9: Sep | M9: Oct | N9: Nov | O9: Dec | P9: 2025
A10: Verteilung so. Aufwand | D10: =D11/$P$11 -> 0.073 | E10: =E11/$P$11 -> 0.061 | F10: =F11/$P$11 -> 0.07 | G10: =G11/$P$11 -> 0.064 | H10: =H11/$P$11 -> 0.237 | I10: =I11/$P$11 -> 0.062 | J10: =J11/$P$11 -> 0.072 | K10: =K11/$P$11 -> 0.061 | ... O10: =O11/$P$11 -> 0.061 | P10: =SUM(D10:O10) -> 1
A11: so. Aufwand | D11: 7300 | E11: 6100 | F11: 7000 | G11: 6400 | H11: 23700 | I11: 6200 | J11: 7200 | K11: 6100 | L11: 10500 | M11: 6400 | N11: 7000 | O11: 6100 | P11: =SUM(D11:O11) -> 100000
A12: Miete | D12: 3750 | E12: 3750 | F12: 3750 | G12: 3750 | H12: 3750 | I12: 3750 | J12: 3750 | K12: 3750 | L12: 3750 | M12: 3750 | N12: 3750 | O12: 3750 | P12: =SUM(D12:O12) -> 45000

Sheet Personal
B1: (in Euro)
E2: Bruttogehalt beginn | G2: =2025 -> 2025
G3: 45658 | H3: 45689 | I3: 45717 | J3: 45748 | K3: 45778 | L3: 45809 | M3: 45839 | N3: 45870 | O3: 45901 | P3: 45931 | Q3: 45962 | R3: 45992
A4: Bestand
A6: 1 | B6: Geschäftsfürhrung | C6: =Annahmen!E49 -> 40 | D6: =Annahmen!D49 -> 7000 | E6: =Annahmen!G49 -> 7000 | F6: 45658 | G6: =$E$6 -> 7000 | H6: =$E$6 -> 7000 | I6: =$E$6 -> 7000 | J6: =$E$6 -> 7000 | K6: =$E$6 -> 7000 | L6: =$E$6 -> 7000 | M6: =$E$6 -> 7000 | N6: =$E$6 -> 7000 | ... R6: =$E$6 -> 7000
A7: =Annahmen!C50 -> 1 | B7: Buchhaltung | C7: =Annahmen!E50 -> 40 | D7: =Annahmen!D50 -> 3300 | E7: =Annahmen!G50 -> 3300 | F7: 45658 | G7: =$E$7 -> 3300 | H7: =$E$7 -> 3300 | I7: =$E$7 -> 3300 | J7: =$E$7 -> 3300 | K7: =$E$7 -> 3300 | L7: =$E$7 -> 3300 | M7: =$E$7 -> 3300 | N7: =$E$7 -> 3300 | ... R7: =$E$7 -> 3300
A8: =Annahmen!C51 -> 2 | B8: Assistenz | C8: =Annahmen!E51 -> 40 | D8: =Annahmen!D51 -> 3300 | E8: =Annahmen!G51 -> 6600 | F8: 45658 | G8: =$E$8 -> 6600 | H8: =$E$8 -> 6600 | I8: =$E$8 -> 6600 | J8: =$E$8 -> 6600 | K8: =$E$8 -> 6600 | L8: =$E$8 -> 6600 | M8: =$E$8 -> 6600 | N8: =$E$8 -> 6600 | ... R8: =$E$8 -> 6600
A9: =Annahmen!C52 -> 1 | B9: Techniker | C9: =Annahmen!E52 -> 40 | D9: =Annahmen!D52 -> 3300 | E9: =Annahmen!G52 -> 3300 | F9: 45658 | G9: =$E$9 -> 3300 | H9: =$E$9 -> 3300 | I9: =$E$9 -> 3300 | J9: =$E$9 -> 3300 | K9: =$E$9 -> 3300 | L9: =$E$9 -> 3300 | M9: =$E$9 -> 3300 | N9: =$E$9 -> 3300 | ... R9: =$E$9 -> 3300
A10: =Annahmen!C54 -> 15 | B10: Informatiker | C10: =Annahmen!E53 -> 40 | D10: =Annahmen!D53 -> 4300 | E10: =Annahmen!G53 -> 64500 | F10: 45658 | G10: =$E$10 -> 64500 | H10: =$E$10 -> 64500 | I10: =$E$10 -> 64500 | J10: =$E$10 -> 64500 | K10: =$E$10 -> 64500 | L10: =$E$10 -> 64500 | M10: =$E$10 -> 64500 | N10: =$E$10 -> 64500 | ... R10: =$E$10 -> 64500
B12: Gesamt - Bestand | G12: =SUM(G6:G10) -> 84700 | H12: =SUM(H6:H10) -> 84700 | I12: =SUM(I6:I10) -> 84700 | J12: =SUM(J6:J10) -> 84700 | K12: =SUM(K6:K10) -> 84700 | L12: =SUM(L6:L10) -> 84700 | M12: =SUM(M6:M10) -> 84700 | N12: =SUM(N6:N10) -> 84700 | ... R12: =SUM(R6:R10) -> 84700
A13: Neu
A15: 15 | B15: Gehaltserhöhung | D15: =Annahmen!D54 -> 700 | E15: =Annahmen!H54 -> 10500 | F15: 46023
B17: Gesamt - Neu
A18: Zusammenfassung
B19: Gesamt(ohne Sozialversicherung) | G19: =G12 -> 84700 | H19: =H12 -> 84700 | I19: =I12 -> 84700 | J19: =J12 -> 84700 | K19: =K12 -> 84700 | L19: =L12 -> 84700 | M19: =M12 -> 84700 | N19: =N12 -> 84700 | ... R19: =R12 -> 84700
B20: Sozialversicherung | C20: =Annahmen!I48 -> 0.219992 | G20: =G19*$C$20 -> 18633.322 | H20: =H19*$C$20 -> 18633.322 | I20: =I19*$C$20 -> 18633.322 | J20: =J19*$C$20 -> 18633.322 | K20: =K19*$C$20 -> 18633.322 | L20: =L19*$C$20 -> 18633.322 | M20: =M19*$C$20 -> 18633.322 | N20: =N19*$C$20 -> 18633.322 | ... R20: =R19*$C$20 -> 18633.322
B21: Gesamt Personal | G21: =SUM(G19:G20) -> 103333.32 | H21: =SUM(H19:H20) -> 103333.32 | I21: =SUM(I19:I20) -> 103333.32 | J21: =SUM(J19:J20) -> 103333.32 | K21: =SUM(K19:K20) -> 103333.32 | L21: =SUM(L19:L20) -> 103333.32 | M21: =SUM(M19:M20) -> 103333.32 | N21: =SUM(N19:N20) -> 103333.32 | ... R21: =SUM(R19:R20) -> 103333.32

Sheet Aufwand
N1: Gesamt
A2: Nettobeträge (in Euro) | B2: Jan | C2: Feb | D2: Mrz | E2: Apr | F2: Mai | G2: Jun | H2: Jul | I2: Aug | J2: Sep | K2: Okt | L2: Nov | M2: Dez | N2: 2025
A4: Verteilung so. Aufwand | B4: =Annahmen!H60 -> 0.073 | C4: =Annahmen!I60 -> 0.061 | D4: =Annahmen!J60 -> 0.07 | E4: =Annahmen!K60 -> 0.064 | F4: =Annahmen!L60 -> 0.237 | G4: =Annahmen!M60 -> 0.062 | H4: =Annahmen!N60 -> 0.072 | I4: =Annahmen!O60 -> 0.061 | ... M4: =Annahmen!S60 -> 0.061 | N4: =SUM(B4:M4) -> 1
A5: Miete | B5: =$N$5/12 -> 3750 | C5: =$N$5/12 -> 3750 | D5: =$N$5/12 -> 3750 | E5: =$N$5/12 -> 3750 | F5: =$N$5/12 -> 3750 | G5: =$N$5/12 -> 3750 | H5: =$N$5/12 -> 3750 | I5: =$N$5/12 -> 3750 | ... M5: =$N$5/12 -> 3750 | N5: =Annahmen!E59 -> 45000
A6: so. Aufwand | N6: =Annahmen!E60 -> 100000

Sheet Kredit
B1: Planung
B2: Ausgaben | C2: Jan | D2: Feb | E2: Mrz | F2: Apr | G2: Mai | H2: Jun | I2: Jul | J2: Aug | K2: Sep | L2: Okt | M2: Nov | N2: Dez
A4: Anuitätendahrlen 1
A5: Tilgung
A6: Zins
A7: Restbetrag

Sheet Investitionen
